autonomize_connector/__init__.py
autonomize_connector/auth/__init__.py
autonomize_connector/auth/api_key.py
autonomize_connector/auth/base_auth.py
autonomize_connector/auth/basic_auth.py
autonomize_connector/auth/bearer_auth.py
autonomize_connector/auth/custom_headers.py
autonomize_connector/auth/factory.py
autonomize_connector/auth/oauth2.py
autonomize_connector/core/__init__.py
autonomize_connector/core/base_connector.py
autonomize_connector/core/exceptions.py
autonomize_connector/core/factory.py
autonomize_connector/core/placeholder_connectors.py
autonomize_connector/core/registration.py
autonomize_connector/core/service_defaults.py
autonomize_connector/core/url_system/__init__.py
autonomize_connector/core/url_system/endpoint_resolver.py
autonomize_connector/core/url_system/service_registry.py
autonomize_connector/core/url_system/url_builder.py
autonomize_connector/utils/__init__.py
autonomize_connector/utils/env_manager.py
autonomize_connector/utils/logger.py
autonomize_connector/utils/validators.py
autonomize_connector_sdk-0.4.0.dist-info/METADATA
autonomize_connector_sdk-0.4.0.dist-info/WHEEL
autonomize_connector_sdk-0.4.0.dist-info/entry_points.txt
autonomize_connector_sdk-0.4.0.dist-info/RECORD
