Metadata-Version: 2.3
Name: autonomize-connector-sdk
Version: 0.4.0
Summary: Industry-leading API integration with JSON-based registration and proven Azure OpenAI support
License: MIT
Keywords: api,connector,sdk,integration,healthcare,jiva,azure,json,openai,oauth2
Author: Autonomize AI
Author-email: team@autonomize.ai
Requires-Python: >=3.12,<3.13
Classifier: Development Status :: 4 - Beta
Classifier: Intended Audience :: Developers
Classifier: License :: OSI Approved :: MIT License
Classifier: Operating System :: OS Independent
Classifier: Programming Language :: Python :: 3
Classifier: Programming Language :: Python :: 3.12
Classifier: Programming Language :: Python :: 3.10
Classifier: Programming Language :: Python :: 3.11
Classifier: Topic :: Internet :: WWW/HTTP
Classifier: Topic :: Software Development :: Libraries :: Python Modules
Classifier: Topic :: System :: Networking
Provides-Extra: all
Provides-Extra: azure
Provides-Extra: oauth1
Provides-Extra: openai
Provides-Extra: salesforce
Requires-Dist: aiohttp (>=3.9.0,<4.0.0)
Requires-Dist: authlib (>=1.3.0,<2.0.0)
Requires-Dist: azure-identity (>=1.15.0,<2.0.0) ; extra == "azure" or extra == "all"
Requires-Dist: cryptography (>=45.0.5,<46.0.0)
Requires-Dist: openai (>=1.10.0,<2.0.0) ; extra == "openai" or extra == "all"
Requires-Dist: orjson (>=3.9.0,<4.0.0)
Requires-Dist: pydantic (>=2.5.0,<3.0.0)
Requires-Dist: python-dotenv (>=1.0.0,<2.0.0)
Requires-Dist: pyyaml (>=6.0,<7.0)
Requires-Dist: requests-oauthlib (>=1.3.0,<2.0.0) ; extra == "oauth1" or extra == "all"
Requires-Dist: simple-salesforce (>=1.12.0,<2.0.0) ; extra == "salesforce" or extra == "all"
Requires-Dist: typing-extensions (>=4.8.0,<5.0.0)
Project-URL: Documentation, https://github.com/autonomize-ai/autonomize-connectors/blob/main/README.md
Project-URL: Homepage, https://github.com/autonomize-ai/autonomize-connectors
Project-URL: Repository, https://github.com/autonomize-ai/autonomize-connectors
